cafram/__init__.py
cafram/common.py
cafram/errors.py
cafram/lib/__init__.py
cafram/lib/flattify.py
cafram/lib/logger.py
cafram/lib/sprint.py
cafram/lib/utils.py
cafram/nodes/__init__.py
cafram/nodes/comp/__init__.py
cafram/nodes/comp/base.py
cafram/nodes/comp/hier.py
cafram/nodes/comp/path.py
cafram/nodes/comp/tree.py
cafram/nodes/ctrl.py
cafram/nodes/engine.py
cafram/utils.py
cafram-0.2.0a0.dist-info/METADATA
cafram-0.2.0a0.dist-info/WHEEL
cafram-0.2.0a0.dist-info/RECORD
