Metadata-Version: 2.1
Name: cafram
Version: 0.2.0a0
Summary: Config as Framework
License: GPL
Author: mrjk
Requires-Python: >=3.8,<4.0
Classifier: License :: Other/Proprietary License
Classifier: Programming Language :: Python :: 3
Classifier: Programming Language :: Python :: 3.8
Classifier: Programming Language :: Python :: 3.9
Classifier: Programming Language :: Python :: 3.10
Classifier: Programming Language :: Python :: 3.11
Requires-Dist: jsonschema (>=4.16.0,<5.0.0)
Requires-Dist: python-log-indenter (>=0.9,<0.10)
Requires-Dist: ruamel.yaml (>=0.17.21,<0.18.0)
Requires-Dist: sh (>=1.14.3,<2.0.0)
